data_helper/__init__.py
data_helper/data_helper.py
tests/__init__.py
tests/test_data_helper.py
automated_data_analysis_pipeline-1.1.0.dist-info/LICENSE
automated_data_analysis_pipeline-1.1.0.dist-info/METADATA
automated_data_analysis_pipeline-1.1.0.dist-info/WHEEL
automated_data_analysis_pipeline-1.1.0.dist-info/top_level.txt
automated_data_analysis_pipeline-1.1.0.dist-info/RECORD
