Metadata-Version: 2.2
Name: automated-data-analysis-pipeline
Version: 1.1.0
Summary: Automated Data Analysis Pipeline
Home-page: https://github.com/vinith-15
Author: VINITH KABILAR
Author-email: vinithkabilar@gmail.com
Keywords: data-analysis automation data-cleaning pandas
Classifier: Programming Language :: Python :: 3
Classifier: License :: OSI Approved :: MIT License
Classifier: Operating System :: OS Independent
Requires-Python: >=3.6
License-File: LICENSE
Requires-Dist: pandas>=1.0.0
Requires-Dist: numpy>=1.18.0
Requires-Dist: openpyxl>=3.0.0
Dynamic: author
Dynamic: author-email
Dynamic: classifier
Dynamic: description
Dynamic: description-content-type
Dynamic: home-page
Dynamic: keywords
Dynamic: requires-dist
Dynamic: requires-python
Dynamic: summary
